CHANGES.txt
COPYING.txt
MANIFEST.in
README.txt
setup.py
hamster_rc/__init__.py
hamster_rc.egg-info/PKG-INFO
hamster_rc.egg-info/SOURCES.txt
hamster_rc.egg-info/dependency_links.txt
hamster_rc.egg-info/entry_points.txt
hamster_rc.egg-info/not-zip-safe
hamster_rc.egg-info/requires.txt
hamster_rc.egg-info/top_level.txt
hamster_rc/media/css/jquery.mobile-1.0a3pre.min.css
hamster_rc/media/css/images/ajax-loader.png
hamster_rc/media/css/images/form-check-off.png
hamster_rc/media/css/images/form-check-on.png
hamster_rc/media/css/images/form-radio-off.png
hamster_rc/media/css/images/form-radio-on.png
hamster_rc/media/css/images/icon-search-black.png
hamster_rc/media/css/images/icons-18-black.png
hamster_rc/media/css/images/icons-18-white.png
hamster_rc/media/css/images/icons-36-black.png
hamster_rc/media/css/images/icons-36-white.png
hamster_rc/media/js/jquery-1.4.4.min.js
hamster_rc/media/js/jquery.mobile-1.0a3pre.min.js
hamster_rc/templates/index.html