Metadata-Version: 1.0
Name: hamster-rc
Version: 0.1.1
Summary: Hamster Remote Control
Home-page: http://bitbucket.org/lgs/hamster-rc/
Author: Lorenzo Gil Sanchez
Author-email: lorenzo.gil.sanchez@gmail.com
License: GPL 3
Keywords: hamster
Platform: UNKNOWN
